{
  "type": "FeatureCollection",
  "features": [
    {
      "type": "Feature",
      "geometry": {
        "type": "Point",
        "coordinates": [
          130.99,
          31.99
        ]
      },
      "properties": {
        "area_code": "763",
        "area_name": "宮崎県南部山沿い",
        "city_code": "4520500",
        "city_name": "小林市",
        "station_code": "4520501",
        "station_name": "小林市真方",
        "station_furigana": "こばやししまかた",
        "pref_name": "宮崎県",
        "pref_code": 45,
        "affiliation": "気象庁",
        "intensity": "2",
        "earthquake_time": "20240910-1227"
      }
    }
  ]
}